fabrant.py
fabrant-0.0.6.dist-info/DESCRIPTION.rst
fabrant-0.0.6.dist-info/METADATA
fabrant-0.0.6.dist-info/metadata.json
fabrant-0.0.6.dist-info/RECORD
fabrant-0.0.6.dist-info/top_level.txt
fabrant-0.0.6.dist-info/WHEEL
