Metadata-Version: 2.0
Name: fabrant
Version: 0.0.6
Summary: Easy handling of vagrant hosts within fabric
Home-page: https://github.com/constantinius/fabrant
Author: Fabian Schindler
Author-email: fabian.schindler@eox.at
License: MIT
Platform: UNKNOWN
Classifier: Programming Language :: Python :: 2
Classifier: Programming Language :: Python :: 3
Classifier: Intended Audience :: Developers
Classifier: License :: OSI Approved :: MIT License
Classifier: Topic :: Software Development :: Libraries
Classifier: Topic :: Utilities
